gaia/__init__.py
gaia/errors.py
gaia/gaia.py
gaia_finder-2.0.0.dist-info/LICENSE
gaia_finder-2.0.0.dist-info/METADATA
gaia_finder-2.0.0.dist-info/WHEEL
gaia_finder-2.0.0.dist-info/entry_points.txt
gaia_finder-2.0.0.dist-info/top_level.txt
gaia_finder-2.0.0.dist-info/RECORD
