Metadata-Version: 2.1
Name: gaia-finder
Version: 2.0.0
Summary: UNKNOWN
Home-page: https://github.com/deadlylaid/gaia
Author: UNKNOWN
Author-email: deadlylaid@gmail.com
License: UNKNOWN
Platform: UNKNOWN
Requires-Dist: click
Requires-Dist: awscli
Requires-Dist: boto3
Requires-Dist: botocore
Requires-Dist: pathlib
Provides-Extra: doc
Requires-Dist: sphinx; extra == 'doc'
Requires-Dist: sphinx-rtd-theme; extra == 'doc'
Provides-Extra: test
Requires-Dist: pytest; extra == 'test'
Requires-Dist: mock; extra == 'test'
Requires-Dist: pytest-cov; extra == 'test'
Requires-Dist: codecov; extra == 'test'
